{
  "success": true,
  "message": "成功",
  "data": {
    "supportPv": false,
    "ifPvcost": false,
    "on": false,
    "sn": "230817040453",
    "houseName": "base新风机",
    "dateList": [
      "00:17:50",
      "01:32:34",
      "02:51:29",
      "03:57:04",
      "05:05:56",
      "06:13:23",
      "07:31:55",
      "08:37:20",
      "09:40:38",
      "10:47:19",
      "11:57:16",
      "13:07:05",
      "14:12:17",
      "15:18:34",
      "16:22:15",
      "17:27:06",
      "18:38:01",
      "19:43:17",
      "20:49:04",
      "21:56:44",
      "23:07:18"
    ],
    "usedList": [
      "0.000",
      "0.000",
      "0.000",
      "0.000",
      "0.000",
      "0.000",
      "0.000",
      "0.070",
      "0.140",
      "0.160",
      "0.160",
      "0.170",
      "0.150",
      "0.150",
      "0.150",
      "0.110",
      "0.030",
      "0.000",
      "0.000",
      "0.000",
      "0.000"
    ],
    "powerUsedDetails": [
      {
        "date": "00:17:50",
        "start": "50.740",
        "end": "50.740",
        "total": "0.000",
        "expense": "0.000"
      },
      {
        "date": "01:32:34",
        "start": "50.740",
        "end": "50.740",
        "total": "0.000",
        "expense": "0.000"
      },
      {
        "date": "02:51:29",
        "start": "50.740",
        "end": "50.740",
        "total": "0.000",
        "expense": "0.000"
      },
      {
        "date": "03:57:04",
        "start": "50.740",
        "end": "50.740",
        "total": "0.000",
        "expense": "0.000"
      },
      {
        "date": "05:05:56",
        "start": "50.740",
        "end": "50.740",
        "total": "0.000",
        "expense": "0.000"
      },
      {
        "date": "06:13:23",
        "start": "50.740",
        "end": "50.740",
        "total": "0.000",
        "expense": "0.000"
      },
      {
        "date": "07:31:55",
        "start": "50.740",
        "end": "50.740",
        "total": "0.000",
        "expense": "0.000"
      },
      {
        "date": "08:37:20",
        "start": "50.740",
        "end": "50.810",
        "total": "0.070",
        "expense": "0.000"
      },
      {
        "date": "09:40:38",
        "start": "50.810",
        "end": "50.950",
        "total": "0.140",
        "expense": "0.000"
      },
      {
        "date": "10:47:19",
        "start": "50.950",
        "end": "51.110",
        "total": "0.160",
        "expense": "0.000"
      },
      {
        "date": "11:57:16",
        "start": "51.110",
        "end": "51.270",
        "total": "0.160",
        "expense": "0.000"
      },
      {
        "date": "13:07:05",
        "start": "51.270",
        "end": "51.440",
        "total": "0.170",
        "expense": "0.000"
      },
      {
        "date": "14:12:17",
        "start": "51.440",
        "end": "51.590",
        "total": "0.150",
        "expense": "0.000"
      },
      {
        "date": "15:18:34",
        "start": "51.590",
        "end": "51.740",
        "total": "0.150",
        "expense": "0.000"
      },
      {
        "date": "16:22:15",
        "start": "51.740",
        "end": "51.890",
        "total": "0.150",
        "expense": "0.000"
      },
      {
        "date": "17:27:06",
        "start": "51.890",
        "end": "52.000",
        "total": "0.110",
        "expense": "0.000"
      },
      {
        "date": "18:38:01",
        "start": "52.000",
        "end": "52.030",
        "total": "0.030",
        "expense": "0.000"
      },
      {
        "date": "19:43:17",
        "start": "52.030",
        "end": "52.030",
        "total": "0.000",
        "expense": "0.000"
      },
      {
        "date": "20:49:04",
        "start": "52.030",
        "end": "52.030",
        "total": "0.000",
        "expense": "0.000"
      },
      {
        "date": "21:56:44",
        "start": "52.030",
        "end": "52.030",
        "total": "0.000",
        "expense": "0.000"
      },
      {
        "date": "23:07:18",
        "start": "52.030",
        "end": "52.030",
        "total": "0.000",
        "expense": "0.000"
      }
    ],
    "hasShare": false,
    "ifShare": false,
    "totalUsed": "1.290",
    "totalAmount": "0.00",
    "type": "YADA"
  }
}