{
  "success": true,
  "message": "成功",
  "data": {
    "supportPv": false,
    "ifPvcost": false,
    "on": false,
    "sn": "230817040504",
    "houseName": "baseGY3",
    "dateList": [
      "08:01:31",
      "09:12:53",
      "10:19:37",
      "11:22:40",
      "12:35:24",
      "13:44:03",
      "14:46:33",
      "15:54:04",
      "16:57:17",
      "18:09:21",
      "19:12:14"
    ],
    "usedList": [
      "0.460",
      "0.490",
      "0.470",
      "0.440",
      "0.500",
      "0.480",
      "0.430",
      "0.470",
      "0.440",
      "0.500",
      "0.440"
    ],
    "powerUsedDetails": [
      {
        "date": "08:01:31",
        "start": "879.660",
        "end": "880.120",
        "total": "0.460",
        "expense": "0.000"
      },
      {
        "date": "09:12:53",
        "start": "880.120",
        "end": "880.610",
        "total": "0.490",
        "expense": "0.000"
      },
      {
        "date": "10:19:37",
        "start": "880.610",
        "end": "881.080",
        "total": "0.470",
        "expense": "0.000"
      },
      {
        "date": "11:22:40",
        "start": "881.080",
        "end": "881.520",
        "total": "0.440",
        "expense": "0.000"
      },
      {
        "date": "12:35:24",
        "start": "881.520",
        "end": "882.020",
        "total": "0.500",
        "expense": "0.000"
      },
      {
        "date": "13:44:03",
        "start": "882.020",
        "end": "882.500",
        "total": "0.480",
        "expense": "0.000"
      },
      {
        "date": "14:46:33",
        "start": "882.500",
        "end": "882.930",
        "total": "0.430",
        "expense": "0.000"
      },
      {
        "date": "15:54:04",
        "start": "882.930",
        "end": "883.400",
        "total": "0.470",
        "expense": "0.000"
      },
      {
        "date": "16:57:17",
        "start": "883.400",
        "end": "883.840",
        "total": "0.440",
        "expense": "0.000"
      },
      {
        "date": "18:09:21",
        "start": "883.840",
        "end": "884.340",
        "total": "0.500",
        "expense": "0.000"
      },
      {
        "date": "19:12:14",
        "start": "884.340",
        "end": "884.780",
        "total": "0.440",
        "expense": "0.000"
      }
    ],
    "hasShare": false,
    "ifShare": false,
    "totalUsed": "5.120",
    "totalAmount": "0.001",
    "type": "YADA"
  }
}