{
  "success": true,
  "message": "成功",
  "data": {
    "supportPv": false,
    "ifPvcost": false,
    "on": false,
    "sn": "230817040545",
    "houseName": "baseGY2",
    "dateList": [
      "08:08:40",
      "09:12:29",
      "10:15:36",
      "11:22:07",
      "12:27:09",
      "13:30:13",
      "14:36:01",
      "15:40:48",
      "16:47:22",
      "17:52:22"
    ],
    "usedList": [
      "0.430",
      "0.440",
      "0.440",
      "0.460",
      "0.460",
      "0.440",
      "0.450",
      "0.450",
      "0.470",
      "0.450"
    ],
    "powerUsedDetails": [
      {
        "date": "08:08:40",
        "start": "526.300",
        "end": "526.730",
        "total": "0.430",
        "expense": "0.000"
      },
      {
        "date": "09:12:29",
        "start": "526.730",
        "end": "527.170",
        "total": "0.440",
        "expense": "0.000"
      },
      {
        "date": "10:15:36",
        "start": "527.170",
        "end": "527.610",
        "total": "0.440",
        "expense": "0.000"
      },
      {
        "date": "11:22:07",
        "start": "527.610",
        "end": "528.070",
        "total": "0.460",
        "expense": "0.000"
      },
      {
        "date": "12:27:09",
        "start": "528.070",
        "end": "528.530",
        "total": "0.460",
        "expense": "0.000"
      },
      {
        "date": "13:30:13",
        "start": "528.530",
        "end": "528.970",
        "total": "0.440",
        "expense": "0.000"
      },
      {
        "date": "14:36:01",
        "start": "528.970",
        "end": "529.420",
        "total": "0.450",
        "expense": "0.000"
      },
      {
        "date": "15:40:48",
        "start": "529.420",
        "end": "529.870",
        "total": "0.450",
        "expense": "0.000"
      },
      {
        "date": "16:47:22",
        "start": "529.870",
        "end": "530.340",
        "total": "0.470",
        "expense": "0.000"
      },
      {
        "date": "17:52:22",
        "start": "530.340",
        "end": "530.790",
        "total": "0.450",
        "expense": "0.000"
      }
    ],
    "hasShare": false,
    "ifShare": false,
    "totalUsed": "4.490",
    "totalAmount": "0.00",
    "type": "YADA"
  }
}